plowman/__init__.py
plowman/__main__.py
plowman/__version__.py
plowman/commands/__init__.py
plowman/commands/base.py
plowman/commands/sow.py
plowman/lib/__init__.py
plowman/lib/cli.py
plowman/lib/constants.py
plowman/lib/estate.py
plowman/lib/exceptions.py
plowman/lib/type_defs.py
plowman/py.typed
plowman-0.3.0.dist-info/WHEEL
plowman-0.3.0.dist-info/entry_points.txt
plowman-0.3.0.dist-info/METADATA
plowman-0.3.0.dist-info/RECORD
