Metadata-Version: 2.3
Name: plowman
Version: 0.3.0
Summary: Dotfile farm manager
Keywords: dotfiles
Author: Stephanos Kuma
Author-email: Stephanos Kuma <stephanos@kuma.ai>
License: BSD-3-Clause
Classifier: Development Status :: 1 - Planning
Classifier: Operating System :: OS Independent
Classifier: Programming Language :: Python :: 3 :: Only
Classifier: License :: OSI Approved :: BSD License
Classifier: Intended Audience :: Developers
Requires-Dist: dj-settings~=8.0
Requires-Dist: jinja2~=3.1
Requires-Dist: pyutilkit~=0.10
Requires-Python: >=3.10
Project-URL: documentation, https://plowman.readthedocs.io/en/stable/
Project-URL: homepage, https://plowman.readthedocs.io/en/stable/
Project-URL: repository, https://github.com/spapanik/plowman/
